bmp384.py
circuitpython_bmp384-0.1.1.dist-info/LICENSE
circuitpython_bmp384-0.1.1.dist-info/METADATA
circuitpython_bmp384-0.1.1.dist-info/WHEEL
circuitpython_bmp384-0.1.1.dist-info/top_level.txt
circuitpython_bmp384-0.1.1.dist-info/RECORD
