Metadata-Version: 2.1
Name: circuitpython-bmp384
Version: 0.1.1
Summary: CircuitPython Driver for the Bosch BMP384 Pressure and Temperature sensor
Author-email: "Jose D. Montoya" <jlib@mailmeto.mozmail.com>
License: MIT
Project-URL: Homepage, https://github.com/jposada202020/CircuitPython_BMP384
Keywords: sensor,blinka,circuitpython,micropython,bmp384,pressure,temperature,driver,sensor,bosch,bmp384
Classifier: Intended Audience :: Developers
Classifier: Topic :: Software Development :: Libraries
Classifier: Topic :: Software Development :: Embedded Systems
Classifier: Topic :: System :: Hardware
Classifier: License :: OSI Approved :: MIT License
Classifier: Programming Language :: Python :: 3
License-File: LICENSE
Requires-Dist: Adafruit-Blinka
Requires-Dist: adafruit-circuitpython-busdevice
Requires-Dist: adafruit-circuitpython-register
Provides-Extra: optional
